<?xml version = '1.0' encoding = 'UTF-8'?>
<InheritanceRelation class="oracle.dbtools.crest.model.design.logical.InheritanceRelation" name="Hierarchy_2" directorySegmentName="seg_0" id="CDEDA8C5-6118-91C2-D705-FF99B10B4190">
<createdBy>filip</createdBy>
<createdTime>2020-04-07 17:57:36 UTC</createdTime>
<ownerDesignName>HelpdeskIT</ownerDesignName>
<engineerTo>
<item key="70A13AAC-EFA1-6039-E5B6-22153185E26C" value="true"/>
</engineerTo>
<identifying>false</identifying>
<nameOnSource>Super Type</nameOnSource>
<nameOnTarget>Sub Type</nameOnTarget>
<optionalSource>true</optionalSource>
<optionalTarget>true</optionalTarget>
<sourceEntity>332FB444-2519-E107-1E01-4CC2CB7AFD71</sourceEntity>
<targetEntity>DCFF930E-7394-2CFA-78AE-AE62088DF723</targetEntity>
<transferable>true</transferable>
<deleteRule>NO ACTION</deleteRule>
</InheritanceRelation>